resctk/__init__.py
resctk/error_messages.py
resctk/info.py
resctk/resume.py
resctk/score.py
resctk-0.1.4.dist-info/licenses/LICENSE
resctk-0.1.4.dist-info/METADATA
resctk-0.1.4.dist-info/WHEEL
resctk-0.1.4.dist-info/top_level.txt
resctk-0.1.4.dist-info/RECORD
