Metadata-Version: 2.4
Name: resctk
Version: 0.1.4
Summary: A powerful AI-driven toolkit for parsing, extracting, scoring, and screening resumes, with customizable pipelines.
Author: Rajdeep Roshan Sahu
License: MIT
Requires-Python: >=3.7
License-File: LICENSE
Requires-Dist: python-docx==1.1.2
Requires-Dist: pdfplumber==0.11.5
Requires-Dist: nltk==3.9.1
Requires-Dist: sentence-transformers==3.4.1
Requires-Dist: spacy==3.8.4
Requires-Dist: scikit-learn==1.6.1
Requires-Dist: numpy==1.26.4
Provides-Extra: dev
Requires-Dist: pytest==8.3.5; extra == "dev"
Dynamic: license-file
